djangocms_zb_youtube/__init__.py
djangocms_zb_youtube/apps.py
djangocms_zb_youtube/cms_plugins.py
djangocms_zb_youtube/models.py
djangocms_zb_youtube/lib/__init__.py
djangocms_zb_youtube/lib/choices.py
djangocms_zb_youtube/locale/es/LC_MESSAGES/django.mo
djangocms_zb_youtube/locale/es/LC_MESSAGES/django.po
djangocms_zb_youtube/migrations/0001_initial.py
djangocms_zb_youtube/migrations/0002_auto_20220517_1414.py
djangocms_zb_youtube/migrations/0003_pluginconfig_playlist_id.py
djangocms_zb_youtube/migrations/__init__.py
djangocms_zb_youtube/templates/djangocms_zb_youtube/zb_youtube.html
djangocms_zb_youtube-1.0.0.dist-info/LICENSE
djangocms_zb_youtube-1.0.0.dist-info/METADATA
djangocms_zb_youtube-1.0.0.dist-info/WHEEL
djangocms_zb_youtube-1.0.0.dist-info/top_level.txt
djangocms_zb_youtube-1.0.0.dist-info/RECORD
