Metadata-Version: 2.2
Name: djangocms-zb-youtube
Version: 1.0.0
Summary: Zibanu Youtube Plugin for Django CMS
Author-email: Mario Ceron <mario.ceron@cqinversiones.co>
License:                     GNU GENERAL PUBLIC LICENSE
Keywords: django,zibanu,youtube,djangocms
Classifier: License :: OSI Approved :: MIT License
Classifier: Programming Language :: Python :: 3.9
Classifier: Development Status :: 5 - Production/Stable
Classifier: Framework :: Django
Classifier: Framework :: Django :: 3.2
Classifier: Environment :: Web Environment
Classifier: Operating System :: OS Independent
Classifier: Topic :: Software Development :: Libraries :: Application Frameworks
Requires-Python: >=3.7
License-File: LICENSE
Requires-Dist: Django~=3.2
Requires-Dist: django-cms>=3.9
Requires-Dist: django-ckeditor
